jnkepler/__init__.py
jnkepler/infer.py
jnkepler/information.py
jnkepler/jnkepler_version.py
jnkepler/data/JaxTTVobject.pkl
jnkepler/data/__init__.py
jnkepler/data/hessian.txt
jnkepler/data/info.txt
jnkepler/data/info_lnpmass.npy
jnkepler/data/info_unconstrained_ref.npy
jnkepler/data/info_unconstrained_ref_lnpmass.npy
jnkepler/data/kep51_4planet.csv
jnkepler/data/kep51_4planet_sol-2.csv
jnkepler/data/kep51_4planet_sol.csv
jnkepler/data/kep51_dt1.0_start155.00_end2950.00_de.csv
jnkepler/data/kep51_dt1.0_start155.00_end2950.00_grad.txt
jnkepler/data/kep51_dt1.0_start155.00_end2950.00_params.txt
jnkepler/data/kep51_dt1.0_start155.00_end2950.00_pdict.csv
jnkepler/data/kep51_dt1.0_start155.00_end2950.00_pdict_ttvfast.csv
jnkepler/data/kep51_dt1.0_start155.00_end2950.00_tc.csv
jnkepler/data/kep51_lc_model.txt
jnkepler/data/kep51_lc_photodtest.csv
jnkepler/data/kep51_nbodytransit_optim.npy
jnkepler/data/kep51_ttv.txt
jnkepler/data/kep51_ttv_photodtest.txt
jnkepler/data/rvs_ttvfast_for_test-ttandrv.txt
jnkepler/data/tcbug_elements.txt
jnkepler/data/tcbug_masses.txt
jnkepler/data/tcs_ttvfast_for_test-all.txt
jnkepler/data/tcs_ttvfast_for_test-nontransiting.txt
jnkepler/data/tcs_ttvfast_for_test-obs-nontransiting.txt
jnkepler/data/tcs_ttvfast_for_test-obs-nontransiting2.txt
jnkepler/data/tcs_ttvfast_for_test-ttandrv.txt
jnkepler/jaxttv/__init__.py
jnkepler/jaxttv/conversion.py
jnkepler/jaxttv/findtransit.py
jnkepler/jaxttv/hermite4.py
jnkepler/jaxttv/infer.py
jnkepler/jaxttv/information.py
jnkepler/jaxttv/jaxttv.py
jnkepler/jaxttv/markley.py
jnkepler/jaxttv/rv.py
jnkepler/jaxttv/symplectic.py
jnkepler/jaxttv/ttvfastutils.py
jnkepler/jaxttv/utils.py
jnkepler/keplerian/__init__.py
jnkepler/keplerian/jacobian.py
jnkepler/keplerian/orbit.py
jnkepler/nbodyrv/__init__.py
jnkepler/nbodyrv/nbodyrv.py
jnkepler/nbodytransit/__init__.py
jnkepler/nbodytransit/nbodytransit.py
jnkepler/nbodytransit/transit.py
jnkepler/tests/__init__.py
jnkepler/tests/read_testdata.py
jnkepler-0.2.4.dist-info/licenses/LICENSE
jnkepler-0.2.4.dist-info/METADATA
jnkepler-0.2.4.dist-info/WHEEL
jnkepler-0.2.4.dist-info/top_level.txt
jnkepler-0.2.4.dist-info/RECORD
