Metadata-Version: 2.4
Name: jnkepler
Version: 0.2.4
Summary: Differentiable JAX N-body code for modeling nearly-Keplerian orbits
Author-email: Kento Masuda <kmasuda@ess.sci.osaka-u.ac.jp>
License: MIT
Project-URL: Homepage, https://github.com/kemasuda/jnkepler
Project-URL: Repository, https://github.com/kemasuda/jnkepler
Project-URL: Documentation, https://github.com/kemasuda/jnkepler
Requires-Python: >=3.10
License-File: LICENSE
Requires-Dist: jax<7.0
Requires-Dist: numpyro
Requires-Dist: pandas
Requires-Dist: numpy
Requires-Dist: matplotlib
Requires-Dist: importlib_resources
Requires-Dist: corner
Requires-Dist: arviz
Dynamic: license-file
